[
    {
      "id": "SPL3-001",
      "parent_id": "SPL2-001",
      "name": "Лікування карієсу та його ускладнень"
    },
    {
      "id": "SPL3-002",
      "parent_id": "SPL2-001",
      "name": "Реставрація зубів"
    },
    {
      "id": "SPL3-003",
      "parent_id": "SPL2-001",
      "name": "Лікування некаріозних уражень"
    },
    {
      "id": "SPL3-004",
      "parent_id": "SPL2-002",
      "name": "Лікування кореневих каналів зубів"
    },
    {
      "id": "SPL3-005",
      "parent_id": "SPL2-002",
      "name": "Перелікування кореневих каналів"
    },
    {
      "id": "SPL3-006",
      "parent_id": "SPL2-002",
      "name": "Апексифікація"
    },
    {
      "id": "SPL3-007",
      "parent_id": "SPL2-002",
      "name": "Видалення сторонніх тіл з каналу"
    },
    {
      "id": "SPL3-008",
      "parent_id": "SPL2-003",
      "name": "Виправлення прикусу"
    },
    {
      "id": "SPL3-009",
      "parent_id": "SPL2-003",
      "name": "Лікування аномалій положення зубів"
    },
    {
      "id": "SPL3-010",
      "parent_id": "SPL2-003",
      "name": "Брекет-системи"
    },
    {
      "id": "SPL3-011",
      "parent_id": "SPL2-003",
      "name": "Елайнери"
    },
    {
      "id": "SPL3-012",
      "parent_id": "SPL2-004",
      "name": "Незнімне протезування (клін.)"
    },
    {
      "id": "SPL3-013",
      "parent_id": "SPL2-004",
      "name": "Знімне протезування (клін.)"
    },
    {
      "id": "SPL3-014",
      "parent_id": "SPL2-004",
      "name": "Коронки / Мости"
    },
    {
      "id": "SPL3-015",
      "parent_id": "SPL2-004",
      "name": "Вініри"
    },
    {
      "id": "SPL3-016",
      "parent_id": "SPL2-004",
      "name": "Вкладки / Накладки"
    },
    {
      "id": "SPL3-017",
      "parent_id": "SPL2-004",
      "name": "Протезування на імплантатах (ортопедичний етап)"
    },
    {
      "id": "SPL3-018",
      "parent_id": "SPL2-005",
      "name": "Професійне чищення зубів"
    },
    {
      "id": "SPL3-019",
      "parent_id": "SPL2-005",
      "name": "Фторування"
    },
    {
      "id": "SPL3-020",
      "parent_id": "SPL2-005",
      "name": "Герметизація фісур"
    },
    {
      "id": "SPL3-021",
      "parent_id": "SPL2-005",
      "name": "Контроль зубного нальоту"
    },
    {
      "id": "SPL3-022",
      "parent_id": "SPL2-006",
      "name": "Рентгенодіагностика"
    },
    {
      "id": "SPL3-023",
      "parent_id": "SPL2-006",
      "name": "Функціональна діагностика"
    },
    {
      "id": "SPL3-024",
      "parent_id": "SPL2-006",
      "name": "Клінічне обстеження / Візуалізація"
    },
    {
      "id": "SPL3-025",
      "parent_id": "SPL2-006",
      "name": "Діагностика вітальності пульпи"
    },
    {
      "id": "SPL3-026",
      "parent_id": "SPL2-007",
      "name": "Видалення зубів"
    },
    {
      "id": "SPL3-027",
      "parent_id": "SPL2-007",
      "name": "Ретенція / Дистопія"
    },
    {
      "id": "SPL3-028",
      "parent_id": "SPL2-007",
      "name": "Хірургічна підготовка під імплантацію"
    },
    {
      "id": "SPL3-029",
      "parent_id": "SPL2-007",
      "name": "Лікування запальних процесів"
    },
    {
      "id": "SPL3-030",
      "parent_id": "SPL2-007",
      "name": "Операції на м’яких тканинах"
    },
    {
      "id": "SPL3-031",
      "parent_id": "SPL2-007",
      "name": "Кісткова пластика / Синус-ліфтинг (хірургічний етап)"
    },
    {
      "id": "SPL3-032",
      "parent_id": "SPL2-008",
      "name": "Встановлення імплантатів"
    },
    {
      "id": "SPL3-033",
      "parent_id": "SPL2-008",
      "name": "Кісткова пластика / Синус-ліфтинг (підготовка)"
    },
    {
      "id": "SPL3-034",
      "parent_id": "SPL2-008",
      "name": "НКР (направлена кісткова регенерація)"
    },
    {
      "id": "SPL3-035",
      "parent_id": "SPL2-008",
      "name": "Протезування на імплантатах (хірургічний етап)"
    },
    {
      "id": "SPL3-036",
      "parent_id": "SPL2-009",
      "name": "Лікування гінгівіту / пародонтиту (консервативне)"
    },
    {
      "id": "SPL3-037",
      "parent_id": "SPL2-009",
      "name": "Професійне чищення пародонтальних кишень"
    },
    {
      "id": "SPL3-038",
      "parent_id": "SPL2-009",
      "name": "Хірургічне лікування пародонтиту"
    },
    {
      "id": "SPL3-039",
      "parent_id": "SPL2-009",
      "name": "Шинування"
    },
    {
      "id": "SPL3-040",
      "parent_id": "SPL2-010",
      "name": "Лікування карієсу у дітей"
    },
    {
      "id": "SPL3-041",
      "parent_id": "SPL2-010",
      "name": "Профілактика у дітей"
    },
    {
      "id": "SPL3-042",
      "parent_id": "SPL2-010",
      "name": "Превентивна ортодонтія / Апарати"
    },
    {
      "id": "SPL3-043",
      "parent_id": "SPL2-010",
      "name": "Адаптація дітей у стоматологічному кріслі"
    },
    {
      "id": "SPL3-044",
      "parent_id": "SPL2-011",
      "name": "Травми щелепно-лицевої ділянки"
    },
    {
      "id": "SPL3-045",
      "parent_id": "SPL2-011",
      "name": "Новоутворення"
    },
    {
      "id": "SPL3-046",
      "parent_id": "SPL2-011",
      "name": "Вроджені / Набуті деформації"
    },
    {
      "id": "SPL3-047",
      "parent_id": "SPL2-012",
      "name": "Каркаси металокерамічні"
    },
    {
      "id": "SPL3-048",
      "parent_id": "SPL2-012",
      "name": "Нанесення кераміки"
    },
    {
      "id": "SPL3-049",
      "parent_id": "SPL2-013",
      "name": "Робота з цирконієм (ZrO2)"
    },
    {
      "id": "SPL3-050",
      "parent_id": "SPL2-013",
      "name": "Робота з прес-керамікою"
    },
    {
      "id": "SPL3-051",
      "parent_id": "SPL2-014",
      "name": "Повні знімні протези"
    },
    {
      "id": "SPL3-052",
      "parent_id": "SPL2-014",
      "name": "Часткові знімні протези"
    },
    {
      "id": "SPL3-053",
      "parent_id": "SPL2-014",
      "name": "Ремонт протезів"
    },
    {
      "id": "SPL3-054",
      "parent_id": "SPL2-015",
      "name": "Вкладки / Накладки / Вініри (Лаб.)"
    },
    {
      "id": "SPL3-055",
      "parent_id": "SPL2-015",
      "name": "Тимчасові конструкції (Лаб.)"
    },
    {
      "id": "SPL3-056",
      "parent_id": "SPL2-016",
      "name": "Капи"
    },
    {
      "id": "SPL3-057",
      "parent_id": "SPL2-016",
      "name": "Непряма фіксація"
    },
    {
      "id": "SPL3-058",
      "parent_id": "SPL2-016",
      "name": "Інші ортодонтичні апарати"
    },
    {
      "id": "SPL3-059",
      "parent_id": "SPL2-017",
      "name": "Сканування моделей"
    },
    {
      "id": "SPL3-060",
      "parent_id": "SPL2-017",
      "name": "Цифрове моделювання"
    },
    {
      "id": "SPL3-061",
      "parent_id": "SPL2-017",
      "name": "Фрезерування"
    },
    {
      "id": "SPL3-062",
      "parent_id": "SPL2-017",
      "name": "3D-друк"
    },
    {
      "id": "SPL3-063",
      "parent_id": "SPL2-018",
      "name": "Індивідуальні абатменти"
    },
    {
      "id": "SPL3-064",
      "parent_id": "SPL2-018",
      "name": "Протетика на імплантатах (лабораторний етап)"
    },
    {
      "id": "SPL3-065",
      "parent_id": "SPL2-018",
      "name": "Хірургічні шаблони"
    }
  ]
  